{
  "resolvedId": "E:/Projects/JavaRayaInternational/website/components/FeatureDetailBlockchain.vue",
  "transforms": [
    {
      "name": "vite:load-fallback",
      "result": "<template>\r\n    <div class=\"main-container\">\r\n      \r\n        <!-- service section start -->\r\n        <section class=\"service-details-wrapper section-padding pb-125\">\r\n            <div class=\"container\">\r\n                <div class=\"row\">\r\n                    <div class=\"col-lg-4 mtn-40 order-2 order-lg-1\">\r\n                        <div class=\"service-details-widget\">\r\n                            <div class=\"service-single-widget mt-40\" :style=\"{backgroundColor: '#f8faff'}\">\r\n                                <h4 class=\"service-widget-title\">Technology Stack</h4>\r\n                                <ul class=\"service-list\">\r\n                                    <li><a href=\"#\">Ethereum based</a></li>\r\n                                    <li><a href=\"#\">Dotnet 8.0 (LTS) and latest version (STS and LTS)</a></li>\r\n                                    <li><a href=\"#\">NodeJS</a></li>\r\n                                    <li><a href=\"#\">Linux Centos 9 </a></li>\r\n                                    <li><a href=\"#\">Smart Contract</a></li>\r\n                                    <li><a href=\"#\">L1 or L2 </a></li>\r\n                                   \r\n                                </ul>\r\n                            </div>\r\n                            <div class=\"service-single-widget mt-40\" :style=\"{backgroundColor: '#f8faff'}\">\r\n                                <h4 class=\"service-widget-title\">Download Docs</h4>\r\n                                <ul class=\"service-list\">\r\n                                    <li>No release yet on github</li>\r\n                                </ul>\r\n                            </div>\r\n                        </div>\r\n                    </div>\r\n                    <div class=\"col-lg-8 order-1 order-lg-2\">\r\n                        <div class=\"service-details\">\r\n                            <div class=\"service-details-thumb\">\r\n                                <!-- <img :src=\"service.imgSrc\" :alt=\"service.title\"> -->\r\n                            </div>\r\n                            <h3 class=\"mt-4 mb-3\">Blockchain</h3>\r\n                            <!-- <p>At CrossChain Marketplace, we are ushering in a new era of global commerce by harnessing the power of blockchain technology. Our platform is designed to address the challenges faced by cross-border transactions, offering innovative solutions that enhance security, transparency, and efficiency.</p> -->\r\n                            <p class=\"mb-0\">Below is our plan the use of Blockchain in our APP</p>\r\n                            <div class=\"row\">\r\n                                <div class=\"col-sm-6\">\r\n                                    <div class=\"service-details-content mt-30\">\r\n                                        <h4>Smart Contract</h4>\r\n                                        <p>We will automate everything using smart contract in the blockchain. This add trust the business</p>\r\n                                    </div>\r\n                                </div>\r\n                                <!-- <div class=\"col-sm-6\">\r\n                                    <div class=\"service-details-content mt-30\">\r\n                                        <h4>Crypto Payment (optional)</h4>\r\n                                        <p>Enlarge capability to pay with crypto such as BTC or ETH for selected vendors and/or large transaction</p>\r\n                                    </div>\r\n                                </div> -->\r\n                               \r\n                            </div>\r\n                        </div>\r\n                    </div>\r\n                </div>\r\n            </div>\r\n        </section>\r\n        <!-- service section end -->\r\n\r\n    </div>\r\n</template>\r\n\r\n<script>\r\n    \r\n</script>\r\n\r\n\r\n",
      "start": 1716878818351,
      "end": 1716878818490,
      "sourcemaps": null
    },
    {
      "name": "nuxt:layer-aliasing",
      "start": 1716878818490,
      "end": 1716878818490,
      "order": "pre"
    },
    {
      "name": "nuxt:layer-aliasing",
      "start": 1716878818490,
      "end": 1716878818490,
      "order": "pre"
    },
    {
      "name": "nuxt:server-devonly:transform",
      "start": 1716878818490,
      "end": 1716878818490,
      "order": "pre"
    },
    {
      "name": "nuxt:server-devonly:transform",
      "start": 1716878818490,
      "end": 1716878818490,
      "order": "pre"
    },
    {
      "name": "nuxt:client-fallback-auto-id",
      "start": 1716878818490,
      "end": 1716878818490,
      "order": "pre"
    },
    {
      "name": "server-only-component-transform",
      "start": 1716878818490,
      "end": 1716878818490,
      "order": "pre"
    },
    {
      "name": "vite:css",
      "start": 1716878818490,
      "end": 1716878818490,
      "order": "normal"
    },
    {
      "name": "vite:esbuild",
      "start": 1716878818490,
      "end": 1716878818490,
      "order": "normal"
    },
    {
      "name": "vite:json",
      "start": 1716878818490,
      "end": 1716878818490,
      "order": "normal"
    },
    {
      "name": "vite:worker",
      "start": 1716878818490,
      "end": 1716878818490,
      "order": "normal"
    },
    {
      "name": "vite:vue",
      "result": "const _sfc_main = {}\nimport { mergeProps as _mergeProps } from \"vue\"\nimport { ssrRenderStyle as _ssrRenderStyle, ssrRenderAttrs as _ssrRenderAttrs } from \"vue/server-renderer\"\n\nfunction _sfc_ssrRender(_ctx, _push, _parent, _attrs) {\n  _push(`<div${\n    _ssrRenderAttrs(_mergeProps({ class: \"main-container\" }, _attrs))\n  }><section class=\"service-details-wrapper section-padding pb-125\"><div class=\"container\"><div class=\"row\"><div class=\"col-lg-4 mtn-40 order-2 order-lg-1\"><div class=\"service-details-widget\"><div class=\"service-single-widget mt-40\" style=\"${\n    _ssrRenderStyle({backgroundColor: '#f8faff'})\n  }\"><h4 class=\"service-widget-title\">Technology Stack</h4><ul class=\"service-list\"><li><a href=\"#\">Ethereum based</a></li><li><a href=\"#\">Dotnet 8.0 (LTS) and latest version (STS and LTS)</a></li><li><a href=\"#\">NodeJS</a></li><li><a href=\"#\">Linux Centos 9 </a></li><li><a href=\"#\">Smart Contract</a></li><li><a href=\"#\">L1 or L2 </a></li></ul></div><div class=\"service-single-widget mt-40\" style=\"${\n    _ssrRenderStyle({backgroundColor: '#f8faff'})\n  }\"><h4 class=\"service-widget-title\">Download Docs</h4><ul class=\"service-list\"><li>No release yet on github</li></ul></div></div></div><div class=\"col-lg-8 order-1 order-lg-2\"><div class=\"service-details\"><div class=\"service-details-thumb\"></div><h3 class=\"mt-4 mb-3\">Blockchain</h3><p class=\"mb-0\">Below is our plan the use of Blockchain in our APP</p><div class=\"row\"><div class=\"col-sm-6\"><div class=\"service-details-content mt-30\"><h4>Smart Contract</h4><p>We will automate everything using smart contract in the blockchain. This add trust the business</p></div></div></div></div></div></div></div></section></div>`)\n}\n\n\nimport { useSSRContext as __vite_useSSRContext } from 'vue'\nconst _sfc_setup = _sfc_main.setup\n_sfc_main.setup = (props, ctx) => {\n  const ssrContext = __vite_useSSRContext()\n  ;(ssrContext.modules || (ssrContext.modules = new Set())).add(\"components/FeatureDetailBlockchain.vue\")\n  return _sfc_setup ? _sfc_setup(props, ctx) : undefined\n}\nimport _export_sfc from '\u0000plugin-vue:export-helper'\nexport default /*#__PURE__*/_export_sfc(_sfc_main, [['ssrRender',_sfc_ssrRender]])",
      "start": 1716878818490,
      "end": 1716878818491,
      "order": "normal",
      "sourcemaps": {
        "version": 3,
        "sources": [
          "E:/Projects/JavaRayaInternational/website/components/FeatureDetailBlockchain.vue"
        ],
        "names": [],
        "mappings": ";;;;EAAA;IAAA,gBAAA,cACS,KAAK,EAAC,gBAAgB,IAD/B;;IAAA,gBAS6E,4BAA4B;;IATzG,gBAqB6E,4BAA4B",
        "sourcesContent": [
          "<template>\r\n    <div class=\"main-container\">\r\n      \r\n        <!-- service section start -->\r\n        <section class=\"service-details-wrapper section-padding pb-125\">\r\n            <div class=\"container\">\r\n                <div class=\"row\">\r\n                    <div class=\"col-lg-4 mtn-40 order-2 order-lg-1\">\r\n                        <div class=\"service-details-widget\">\r\n                            <div class=\"service-single-widget mt-40\" :style=\"{backgroundColor: '#f8faff'}\">\r\n                                <h4 class=\"service-widget-title\">Technology Stack</h4>\r\n                                <ul class=\"service-list\">\r\n                                    <li><a href=\"#\">Ethereum based</a></li>\r\n                                    <li><a href=\"#\">Dotnet 8.0 (LTS) and latest version (STS and LTS)</a></li>\r\n                                    <li><a href=\"#\">NodeJS</a></li>\r\n                                    <li><a href=\"#\">Linux Centos 9 </a></li>\r\n                                    <li><a href=\"#\">Smart Contract</a></li>\r\n                                    <li><a href=\"#\">L1 or L2 </a></li>\r\n                                   \r\n                                </ul>\r\n                            </div>\r\n                            <div class=\"service-single-widget mt-40\" :style=\"{backgroundColor: '#f8faff'}\">\r\n                                <h4 class=\"service-widget-title\">Download Docs</h4>\r\n                                <ul class=\"service-list\">\r\n                                    <li>No release yet on github</li>\r\n                                </ul>\r\n                            </div>\r\n                        </div>\r\n                    </div>\r\n                    <div class=\"col-lg-8 order-1 order-lg-2\">\r\n                        <div class=\"service-details\">\r\n                            <div class=\"service-details-thumb\">\r\n                                <!-- <img :src=\"service.imgSrc\" :alt=\"service.title\"> -->\r\n                            </div>\r\n                            <h3 class=\"mt-4 mb-3\">Blockchain</h3>\r\n                            <!-- <p>At CrossChain Marketplace, we are ushering in a new era of global commerce by harnessing the power of blockchain technology. Our platform is designed to address the challenges faced by cross-border transactions, offering innovative solutions that enhance security, transparency, and efficiency.</p> -->\r\n                            <p class=\"mb-0\">Below is our plan the use of Blockchain in our APP</p>\r\n                            <div class=\"row\">\r\n                                <div class=\"col-sm-6\">\r\n                                    <div class=\"service-details-content mt-30\">\r\n                                        <h4>Smart Contract</h4>\r\n                                        <p>We will automate everything using smart contract in the blockchain. This add trust the business</p>\r\n                                    </div>\r\n                                </div>\r\n                                <!-- <div class=\"col-sm-6\">\r\n                                    <div class=\"service-details-content mt-30\">\r\n                                        <h4>Crypto Payment (optional)</h4>\r\n                                        <p>Enlarge capability to pay with crypto such as BTC or ETH for selected vendors and/or large transaction</p>\r\n                                    </div>\r\n                                </div> -->\r\n                               \r\n                            </div>\r\n                        </div>\r\n                    </div>\r\n                </div>\r\n            </div>\r\n        </section>\r\n        <!-- service section end -->\r\n\r\n    </div>\r\n</template>\r\n\r\n<script>\r\n    \r\n</script>\r\n\r\n\r\n"
        ]
      }
    },
    {
      "name": "vite:vue-jsx",
      "start": 1716878818491,
      "end": 1716878818491,
      "order": "normal"
    },
    {
      "name": "replace",
      "start": 1716878818491,
      "end": 1716878818491,
      "order": "normal"
    },
    {
      "name": "replace",
      "start": 1716878818491,
      "end": 1716878818491,
      "order": "normal"
    },
    {
      "name": "nuxt:remove-plugin-metadata",
      "start": 1716878818491,
      "end": 1716878818491,
      "order": "normal"
    },
    {
      "name": "nuxt:remove-plugin-metadata",
      "start": 1716878818491,
      "end": 1716878818491,
      "order": "normal"
    },
    {
      "name": "nuxt:components:imports",
      "start": 1716878818491,
      "end": 1716878818491,
      "order": "normal"
    },
    {
      "name": "replace",
      "start": 1716878818491,
      "end": 1716878818491,
      "order": "normal"
    },
    {
      "name": "ssr-styles",
      "start": 1716878818491,
      "end": 1716878818491,
      "order": "normal"
    },
    {
      "name": "vite:define",
      "start": 1716878818491,
      "end": 1716878818491,
      "order": "normal"
    },
    {
      "name": "vite:css-post",
      "start": 1716878818491,
      "end": 1716878818491,
      "order": "normal"
    },
    {
      "name": "vite:build-html",
      "start": 1716878818491,
      "end": 1716878818491,
      "order": "normal"
    },
    {
      "name": "vite:worker-import-meta-url",
      "start": 1716878818491,
      "end": 1716878818491,
      "order": "normal"
    },
    {
      "name": "vite:asset-import-meta-url",
      "start": 1716878818492,
      "end": 1716878818492,
      "order": "normal"
    },
    {
      "name": "commonjs",
      "start": 1716878818492,
      "end": 1716878818492,
      "order": "normal"
    },
    {
      "name": "vite:dynamic-import-vars",
      "start": 1716878818492,
      "end": 1716878818492,
      "order": "normal"
    },
    {
      "name": "vite:import-glob",
      "start": 1716878818492,
      "end": 1716878818492,
      "order": "normal"
    },
    {
      "name": "nuxt:composable-keys",
      "start": 1716878818492,
      "end": 1716878818492,
      "order": "post"
    },
    {
      "name": "nuxt:composable-keys",
      "start": 1716878818492,
      "end": 1716878818492,
      "order": "post"
    },
    {
      "name": "nuxt:imports-transform",
      "start": 1716878818492,
      "end": 1716878818492,
      "order": "post"
    },
    {
      "name": "nuxt:imports-transform",
      "start": 1716878818492,
      "end": 1716878818492,
      "order": "post"
    },
    {
      "name": "unctx:transform",
      "start": 1716878818492,
      "end": 1716878818492,
      "order": "post"
    },
    {
      "name": "unctx:transform",
      "start": 1716878818492,
      "end": 1716878818492,
      "order": "post"
    },
    {
      "name": "nuxt:pages-macros-transform",
      "start": 1716878818492,
      "end": 1716878818492,
      "order": "post"
    },
    {
      "name": "nuxt:pages-macros-transform",
      "start": 1716878818492,
      "end": 1716878818492,
      "order": "post"
    },
    {
      "name": "nuxt:tree-shake-template",
      "start": 1716878818492,
      "end": 1716878818492,
      "order": "post"
    },
    {
      "name": "nuxt:components-loader",
      "start": 1716878818492,
      "end": 1716878818492,
      "order": "post"
    },
    {
      "name": "nuxt:tree-shake-composables:transform",
      "start": 1716878818492,
      "end": 1716878818492,
      "order": "post"
    },
    {
      "name": "vite:build-import-analysis",
      "start": 1716878818492,
      "end": 1716878818492,
      "order": "normal"
    },
    {
      "name": "vite:reporter",
      "start": 1716878818492,
      "end": 1716878818492,
      "order": "normal"
    }
  ]
}
