{
  "resolvedId": "E:/Projects/JavaRayaInternational/website/pages/blog/index.vue",
  "transforms": [
    {
      "name": "vite:load-fallback",
      "result": "<template>\r\n    <div class=\"main-container\">\r\n        <TheHeader />\r\n        <OffCanvasMobileMenu />\r\n        <SearchPopup />\r\n        <BreadcrumbOne activePageName=\"Blog Grid\" title=\"Find all our latest news, insights, and events\" backgroundUrl= \"/images/bg/breadcrumb-bg-four.jpg\" />\r\n\r\n        <!-- Blog Section Start -->\r\n        <div class=\"section-padding fix\">\r\n            <div class=\"container\">\r\n                <div class=\"row row-cols-lg-3 row-cols-md-2 row-cols-sm-2 row-cols-1 mtn-30\">\r\n                    <div class=\"col mt-30\" v-for=\"(blog, index) in blogData\" :key=\"index\">\r\n                        <BlogGridItem :blog=\"blog\" />\r\n                    </div>\r\n                </div>\r\n\r\n                <div class=\"row mt-50\">\r\n                    <div class=\"col\">\r\n                        <ul class=\"pagination center\">\r\n                            <li class=\"page-item\">\r\n                                <a href=\"#\"><i class=\"fa fa-angle-left\"></i></a>\r\n                            </li>\r\n                            <li class=\"page-item active\">\r\n                                <a href=\"#\">1</a>\r\n                            </li>\r\n                            <li class=\"page-item\">\r\n                                <a href=\"#\">2</a>\r\n                            </li>\r\n                            <li class=\"page-item\">\r\n                                <a href=\"#\">3</a>\r\n                            </li>\r\n                            <li class=\"page-item\">\r\n                                <a href=\"#\"><i class=\"fa fa-angle-right\"></i></a>\r\n                            </li>\r\n                        </ul>\r\n                    </div>\r\n                </div>\r\n            </div>\r\n        </div>\r\n        <!-- Blog Section End -->\r\n\r\n        <CallToActionTwo />\r\n        <TheFooter />\r\n    </div>\r\n</template>\r\n\r\n<script>\r\n    import blogData from \"~/data/blog.json\"\r\n\r\n    export default {\r\n        data() {\r\n            return {\r\n                blogData\r\n            }\r\n        },\r\n    };\r\n</script>\r\n\r\n\r\n",
      "start": 1715842299948,
      "end": 1715842300018,
      "sourcemaps": null
    },
    {
      "name": "nuxt:layer-aliasing",
      "start": 1715842300018,
      "end": 1715842300018,
      "order": "pre"
    },
    {
      "name": "nuxt:layer-aliasing",
      "start": 1715842300018,
      "end": 1715842300018,
      "order": "pre"
    },
    {
      "name": "nuxt:server-devonly:transform",
      "start": 1715842300018,
      "end": 1715842300018,
      "order": "pre"
    },
    {
      "name": "nuxt:server-devonly:transform",
      "start": 1715842300018,
      "end": 1715842300018,
      "order": "pre"
    },
    {
      "name": "nuxt:client-fallback-auto-id",
      "start": 1715842300018,
      "end": 1715842300018,
      "order": "pre"
    },
    {
      "name": "server-only-component-transform",
      "start": 1715842300018,
      "end": 1715842300018,
      "order": "pre"
    },
    {
      "name": "vite:css",
      "start": 1715842300018,
      "end": 1715842300018,
      "order": "normal"
    },
    {
      "name": "vite:esbuild",
      "start": 1715842300018,
      "end": 1715842300018,
      "order": "normal"
    },
    {
      "name": "vite:json",
      "start": 1715842300018,
      "end": 1715842300018,
      "order": "normal"
    },
    {
      "name": "vite:worker",
      "start": 1715842300018,
      "end": 1715842300018,
      "order": "normal"
    },
    {
      "name": "vite:vue",
      "result": "\r\n    import blogData from \"~/data/blog.json\"\r\n\r\n    const _sfc_main = {\r\n        data() {\r\n            return {\r\n                blogData\r\n            }\r\n        },\r\n    };\r\n\nimport { resolveComponent as _resolveComponent, mergeProps as _mergeProps } from \"vue\"\nimport { ssrRenderComponent as _ssrRenderComponent, ssrRenderAttrs as _ssrRenderAttrs, ssrRenderList as _ssrRenderList } from \"vue/server-renderer\"\n\nfunction _sfc_ssrRender(_ctx, _push, _parent, _attrs, $props, $setup, $data, $options) {\n  const _component_TheHeader = _resolveComponent(\"TheHeader\")\n  const _component_OffCanvasMobileMenu = _resolveComponent(\"OffCanvasMobileMenu\")\n  const _component_SearchPopup = _resolveComponent(\"SearchPopup\")\n  const _component_BreadcrumbOne = _resolveComponent(\"BreadcrumbOne\")\n  const _component_BlogGridItem = _resolveComponent(\"BlogGridItem\")\n  const _component_CallToActionTwo = _resolveComponent(\"CallToActionTwo\")\n  const _component_TheFooter = _resolveComponent(\"TheFooter\")\n\n  _push(`<div${_ssrRenderAttrs(_mergeProps({ class: \"main-container\" }, _attrs))}>`)\n  _push(_ssrRenderComponent(_component_TheHeader, null, null, _parent))\n  _push(_ssrRenderComponent(_component_OffCanvasMobileMenu, null, null, _parent))\n  _push(_ssrRenderComponent(_component_SearchPopup, null, null, _parent))\n  _push(_ssrRenderComponent(_component_BreadcrumbOne, {\n    activePageName: \"Blog Grid\",\n    title: \"Find all our latest news, insights, and events\",\n    backgroundUrl: \"/images/bg/breadcrumb-bg-four.jpg\"\n  }, null, _parent))\n  _push(`<div class=\"section-padding fix\"><div class=\"container\"><div class=\"row row-cols-lg-3 row-cols-md-2 row-cols-sm-2 row-cols-1 mtn-30\"><!--[-->`)\n  _ssrRenderList($data.blogData, (blog, index) => {\n    _push(`<div class=\"col mt-30\">`)\n    _push(_ssrRenderComponent(_component_BlogGridItem, { blog: blog }, null, _parent))\n    _push(`</div>`)\n  })\n  _push(`<!--]--></div><div class=\"row mt-50\"><div class=\"col\"><ul class=\"pagination center\"><li class=\"page-item\"><a href=\"#\"><i class=\"fa fa-angle-left\"></i></a></li><li class=\"page-item active\"><a href=\"#\">1</a></li><li class=\"page-item\"><a href=\"#\">2</a></li><li class=\"page-item\"><a href=\"#\">3</a></li><li class=\"page-item\"><a href=\"#\"><i class=\"fa fa-angle-right\"></i></a></li></ul></div></div></div></div>`)\n  _push(_ssrRenderComponent(_component_CallToActionTwo, null, null, _parent))\n  _push(_ssrRenderComponent(_component_TheFooter, null, null, _parent))\n  _push(`</div>`)\n}\n\n\nimport { useSSRContext as __vite_useSSRContext } from 'vue'\nconst _sfc_setup = _sfc_main.setup\n_sfc_main.setup = (props, ctx) => {\n  const ssrContext = __vite_useSSRContext()\n  ;(ssrContext.modules || (ssrContext.modules = new Set())).add(\"pages/blog/index.vue\")\n  return _sfc_setup ? _sfc_setup(props, ctx) : undefined\n}\nimport _export_sfc from '\u0000plugin-vue:export-helper'\nexport default /*#__PURE__*/_export_sfc(_sfc_main, [['ssrRender',_sfc_ssrRender]])",
      "start": 1715842300018,
      "end": 1715842300019,
      "order": "normal",
      "sourcemaps": {
        "version": 3,
        "file": "E:/Projects/JavaRayaInternational/website/pages/blog/index.vue",
        "names": [],
        "sources": [
          "E:/Projects/JavaRayaInternational/website/pages/blog/index.vue"
        ],
        "sourcesContent": [
          "<template>\r\n    <div class=\"main-container\">\r\n        <TheHeader />\r\n        <OffCanvasMobileMenu />\r\n        <SearchPopup />\r\n        <BreadcrumbOne activePageName=\"Blog Grid\" title=\"Find all our latest news, insights, and events\" backgroundUrl= \"/images/bg/breadcrumb-bg-four.jpg\" />\r\n\r\n        <!-- Blog Section Start -->\r\n        <div class=\"section-padding fix\">\r\n            <div class=\"container\">\r\n                <div class=\"row row-cols-lg-3 row-cols-md-2 row-cols-sm-2 row-cols-1 mtn-30\">\r\n                    <div class=\"col mt-30\" v-for=\"(blog, index) in blogData\" :key=\"index\">\r\n                        <BlogGridItem :blog=\"blog\" />\r\n                    </div>\r\n                </div>\r\n\r\n                <div class=\"row mt-50\">\r\n                    <div class=\"col\">\r\n                        <ul class=\"pagination center\">\r\n                            <li class=\"page-item\">\r\n                                <a href=\"#\"><i class=\"fa fa-angle-left\"></i></a>\r\n                            </li>\r\n                            <li class=\"page-item active\">\r\n                                <a href=\"#\">1</a>\r\n                            </li>\r\n                            <li class=\"page-item\">\r\n                                <a href=\"#\">2</a>\r\n                            </li>\r\n                            <li class=\"page-item\">\r\n                                <a href=\"#\">3</a>\r\n                            </li>\r\n                            <li class=\"page-item\">\r\n                                <a href=\"#\"><i class=\"fa fa-angle-right\"></i></a>\r\n                            </li>\r\n                        </ul>\r\n                    </div>\r\n                </div>\r\n            </div>\r\n        </div>\r\n        <!-- Blog Section End -->\r\n\r\n        <CallToActionTwo />\r\n        <TheFooter />\r\n    </div>\r\n</template>\r\n\r\n<script>\r\n    import blogData from \"~/data/blog.json\"\r\n\r\n    export default {\r\n        data() {\r\n            return {\r\n                blogData\r\n            }\r\n        },\r\n    };\r\n</script>\r\n\r\n\r\n"
        ],
        "mappings": ";IA+CI,CAAC,CAAC,CAAC,CAAC,CAAC,EAAE,CAAC,CAAC,CAAC,CAAC,CAAC,CAAC,CAAC,EAAE,CAAC,CAAC,CAAC,EAAE,CAAC,CAAC,CAAC,CAAC,CAAC,CAAC,CAAC,CAAC,CAAC,CAAC,CAAC,CAAC,CAAC,CAAC,CAAC,CAAC,CAAC;;IAEtC,CAAC,CAAC,CAAC,CAAC,CAAC,EAAE,CAAC,CAAC,CAAC,CAAC,CAAC,CAAC,EAAE;QACX,CAAC,CAAC,CAAC,CAAC,CAAC,EAAE;YACH,CAAC,CAAC,CAAC,CAAC,CAAC,EAAE;gBACH,CAAC,CAAC,CAAC,CAAC,CAAC,CAAC,CAAC;YACX;QACJ,CAAC;IACL,CAAC;;;;;;;;;;;;;;EAvDL,aAAA,gBAAA,cACS,KAAK,EAAC,gBAAgB,IAD/B;EAAA,MAAA;EAAA,MAAA;EAAA,MAAA;EAAA,MAAA;IAKuB,cAAc,EAAC,WAAW;IAAC,KAAK,EAAC,gDAAgD;IAAC,aAAa,EAAE,mCAAmC;;EAL3J;EAAA,eAWmE,cAAQ,EAX3E,CAWmD,IAAI,EAAE,KAAK;IAX9D;IAAA,MAAA,+CAYuC,IAAI,EAAE,IAAI;IAZjD;;EAAA;EAAA,MAAA;EAAA,MAAA;EAAA"
      }
    },
    {
      "name": "vite:vue-jsx",
      "start": 1715842300019,
      "end": 1715842300019,
      "order": "normal"
    },
    {
      "name": "replace",
      "start": 1715842300019,
      "end": 1715842300019,
      "order": "normal"
    },
    {
      "name": "replace",
      "start": 1715842300019,
      "end": 1715842300019,
      "order": "normal"
    },
    {
      "name": "nuxt:remove-plugin-metadata",
      "start": 1715842300019,
      "end": 1715842300019,
      "order": "normal"
    },
    {
      "name": "nuxt:remove-plugin-metadata",
      "start": 1715842300019,
      "end": 1715842300019,
      "order": "normal"
    },
    {
      "name": "nuxt:components:imports",
      "start": 1715842300019,
      "end": 1715842300019,
      "order": "normal"
    },
    {
      "name": "replace",
      "start": 1715842300019,
      "end": 1715842300019,
      "order": "normal"
    },
    {
      "name": "ssr-styles",
      "start": 1715842300019,
      "end": 1715842300019,
      "order": "normal"
    },
    {
      "name": "vite:define",
      "start": 1715842300019,
      "end": 1715842300019,
      "order": "normal"
    },
    {
      "name": "vite:css-post",
      "start": 1715842300019,
      "end": 1715842300019,
      "order": "normal"
    },
    {
      "name": "vite:build-html",
      "start": 1715842300019,
      "end": 1715842300019,
      "order": "normal"
    },
    {
      "name": "vite:worker-import-meta-url",
      "start": 1715842300019,
      "end": 1715842300019,
      "order": "normal"
    },
    {
      "name": "vite:asset-import-meta-url",
      "start": 1715842300020,
      "end": 1715842300020,
      "order": "normal"
    },
    {
      "name": "commonjs",
      "start": 1715842300020,
      "end": 1715842300020,
      "order": "normal"
    },
    {
      "name": "vite:dynamic-import-vars",
      "start": 1715842300020,
      "end": 1715842300020,
      "order": "normal"
    },
    {
      "name": "vite:import-glob",
      "start": 1715842300020,
      "end": 1715842300020,
      "order": "normal"
    },
    {
      "name": "nuxt:composable-keys",
      "start": 1715842300020,
      "end": 1715842300020,
      "order": "post"
    },
    {
      "name": "nuxt:composable-keys",
      "start": 1715842300020,
      "end": 1715842300020,
      "order": "post"
    },
    {
      "name": "nuxt:imports-transform",
      "start": 1715842300020,
      "end": 1715842300020,
      "order": "post"
    },
    {
      "name": "nuxt:imports-transform",
      "start": 1715842300020,
      "end": 1715842300020,
      "order": "post"
    },
    {
      "name": "unctx:transform",
      "start": 1715842300020,
      "end": 1715842300020,
      "order": "post"
    },
    {
      "name": "unctx:transform",
      "start": 1715842300020,
      "end": 1715842300020,
      "order": "post"
    },
    {
      "name": "nuxt:pages-macros-transform",
      "start": 1715842300020,
      "end": 1715842300020,
      "order": "post"
    },
    {
      "name": "nuxt:pages-macros-transform",
      "start": 1715842300020,
      "end": 1715842300020,
      "order": "post"
    },
    {
      "name": "nuxt:tree-shake-template",
      "start": 1715842300020,
      "end": 1715842300020,
      "order": "post"
    },
    {
      "name": "nuxt:components-loader",
      "result": "import { default as __nuxt_component_0 } from \"E:/Projects/JavaRayaInternational/website/components/TheHeader.vue\";\nimport { default as __nuxt_component_1 } from \"E:/Projects/JavaRayaInternational/website/components/OffCanvasMobileMenu.vue\";\nimport { default as __nuxt_component_2 } from \"E:/Projects/JavaRayaInternational/website/components/SearchPopup.vue\";\nimport { default as __nuxt_component_3 } from \"E:/Projects/JavaRayaInternational/website/components/BreadcrumbOne.vue\";\nimport { default as __nuxt_component_4 } from \"E:/Projects/JavaRayaInternational/website/components/BlogGridItem.vue\";\nimport { default as __nuxt_component_5 } from \"E:/Projects/JavaRayaInternational/website/components/CallToActionTwo.vue\";\nimport { default as __nuxt_component_6 } from \"E:/Projects/JavaRayaInternational/website/components/TheFooter.vue\";\n\r\n    import blogData from \"~/data/blog.json\"\r\n\r\n    const _sfc_main = {\r\n        data() {\r\n            return {\r\n                blogData\r\n            }\r\n        },\r\n    };\r\n\nimport { resolveComponent as _resolveComponent, mergeProps as _mergeProps } from \"vue\"\nimport { ssrRenderComponent as _ssrRenderComponent, ssrRenderAttrs as _ssrRenderAttrs, ssrRenderList as _ssrRenderList } from \"vue/server-renderer\"\n\nfunction _sfc_ssrRender(_ctx, _push, _parent, _attrs, $props, $setup, $data, $options) {\n  const _component_TheHeader = __nuxt_component_0\n  const _component_OffCanvasMobileMenu = __nuxt_component_1\n  const _component_SearchPopup = __nuxt_component_2\n  const _component_BreadcrumbOne = __nuxt_component_3\n  const _component_BlogGridItem = __nuxt_component_4\n  const _component_CallToActionTwo = __nuxt_component_5\n  const _component_TheFooter = __nuxt_component_6\n\n  _push(`<div${_ssrRenderAttrs(_mergeProps({ class: \"main-container\" }, _attrs))}>`)\n  _push(_ssrRenderComponent(_component_TheHeader, null, null, _parent))\n  _push(_ssrRenderComponent(_component_OffCanvasMobileMenu, null, null, _parent))\n  _push(_ssrRenderComponent(_component_SearchPopup, null, null, _parent))\n  _push(_ssrRenderComponent(_component_BreadcrumbOne, {\n    activePageName: \"Blog Grid\",\n    title: \"Find all our latest news, insights, and events\",\n    backgroundUrl: \"/images/bg/breadcrumb-bg-four.jpg\"\n  }, null, _parent))\n  _push(`<div class=\"section-padding fix\"><div class=\"container\"><div class=\"row row-cols-lg-3 row-cols-md-2 row-cols-sm-2 row-cols-1 mtn-30\"><!--[-->`)\n  _ssrRenderList($data.blogData, (blog, index) => {\n    _push(`<div class=\"col mt-30\">`)\n    _push(_ssrRenderComponent(_component_BlogGridItem, { blog: blog }, null, _parent))\n    _push(`</div>`)\n  })\n  _push(`<!--]--></div><div class=\"row mt-50\"><div class=\"col\"><ul class=\"pagination center\"><li class=\"page-item\"><a href=\"#\"><i class=\"fa fa-angle-left\"></i></a></li><li class=\"page-item active\"><a href=\"#\">1</a></li><li class=\"page-item\"><a href=\"#\">2</a></li><li class=\"page-item\"><a href=\"#\">3</a></li><li class=\"page-item\"><a href=\"#\"><i class=\"fa fa-angle-right\"></i></a></li></ul></div></div></div></div>`)\n  _push(_ssrRenderComponent(_component_CallToActionTwo, null, null, _parent))\n  _push(_ssrRenderComponent(_component_TheFooter, null, null, _parent))\n  _push(`</div>`)\n}\n\n\nimport { useSSRContext as __vite_useSSRContext } from 'vue'\nconst _sfc_setup = _sfc_main.setup\n_sfc_main.setup = (props, ctx) => {\n  const ssrContext = __vite_useSSRContext()\n  ;(ssrContext.modules || (ssrContext.modules = new Set())).add(\"pages/blog/index.vue\")\n  return _sfc_setup ? _sfc_setup(props, ctx) : undefined\n}\nimport _export_sfc from '\u0000plugin-vue:export-helper'\nexport default /*#__PURE__*/_export_sfc(_sfc_main, [['ssrRender',_sfc_ssrRender]])",
      "start": 1715842300020,
      "end": 1715842300020,
      "order": "post",
      "sourcemaps": {
        "version": 3,
        "sources": [
          ""
        ],
        "names": [],
        "mappings": ";;;;;;;AAAA,CAAC;AACD,CAAC,CAAC,CAAC,CAAC,CAAC,CAAC,CAAC,CAAC,CAAC,CAAC,CAAC,CAAC,CAAC,CAAC,CAAC,CAAC,CAAC,CAAC,CAAC,CAAC,CAAC,CAAC,CAAC,CAAC,CAAC,CAAC,CAAC,CAAC,CAAC,CAAC,CAAC,CAAC,CAAC,CAAC,CAAC,CAAC,CAAC,CAAC,CAAC,CAAC,CAAC,CAAC,CAAC,CAAC;AAC5C,CAAC;AACD,CAAC,CAAC,CAAC,CAAC,CAAC,CAAC,CAAC,CAAC,CAAC,CAAC,CAAC,CAAC,CAAC,CAAC,CAAC,CAAC,CAAC,CAAC,CAAC,CAAC,CAAC,CAAC,CAAC,CAAC;AACxB,CAAC,CAAC,CAAC,CAAC,CAAC,CAAC,CAAC,CAAC,CAAC,CAAC,CAAC,CAAC,CAAC,CAAC,CAAC,CAAC,CAAC;AACjB,CAAC,CAAC,CAAC,CAAC,CAAC,CAAC,CAAC,CAAC,CAAC,CAAC,CAAC,CAAC,CAAC,CAAC,CAAC,CAAC,CAAC,CAAC,CAAC,CAAC,CAAC;AACrB,CAAC,CAAC,CAAC,CAAC,CAAC,CAAC,CAAC,CAAC,CAAC,CAAC,CAAC,CAAC,CAAC,CAAC,CAAC,CAAC,CAAC,CAAC,CAAC,CAAC,CAAC,CAAC,CAAC,CAAC,CAAC;AACzB,CAAC,CAAC,CAAC,CAAC,CAAC,CAAC,CAAC,CAAC,CAAC,CAAC,CAAC,CAAC,CAAC,CAAC;AACd,CAAC,CAAC,CAAC,CAAC,CAAC,CAAC,CAAC,CAAC,CAAC,CAAC,CAAC;AACX,CAAC,CAAC,CAAC,CAAC,CAAC,CAAC,CAAC;AACP;AACA,CAAC,CAAC,CAAC,CAAC,CAAC,CAAC,CAAC,CAAC,CAAC,CAAC,CAAC,CAAC,CAAC,CAAC,CAAC,CAAC,CAAC,CAAC,CAAC,CAAC,CAAC,CAAC,CAAC,CAAC,CAAC,CAAC,CAAC,CAAC,CAAC,CAAC,CAAC,CAAC,CAAC,CAAC,CAAC,CAAC,CAAC,CAAC,CAAC,CAAC,CAAC,CAAC,CAAC,CAAC,CAAC,CAAC,CAAC,CAAC,CAAC,CAAC,CAAC,CAAC,CAAC,CAAC,CAAC,CAAC,CAAC,CAAC,CAAC,CAAC,CAAC,CAAC,CAAC,CAAC,CAAC,CAAC,CAAC,CAAC,CAAC,CAAC,CAAC,CAAC,CAAC,CAAC,CAAC,CAAC,CAAC,CAAC,CAAC,CAAC,CAAC,CAAC,CAAC,CAAC,CAAC,CAAC;AACtF,CAAC,CAAC,CAAC,CAAC,CAAC,CAAC,CAAC,CAAC,CAAC,CAAC,CAAC,CAAC,CAAC,CAAC,CAAC,CAAC,CAAC,CAAC,CAAC,CAAC,CAAC,CAAC,CAAC,CAAC,CAAC,CAAC,CAAC,CAAC,CAAC,CAAC,CAAC,CAAC,CAAC,CAAC,CAAC,CAAC,CAAC,CAAC,CAAC,CAAC,CAAC,CAAC,CAAC,CAAC,CAAC,CAAC,CAAC,CAAC,CAAC,CAAC,CAAC,CAAC,CAAC,CAAC,CAAC,CAAC,CAAC,CAAC,CAAC,CAAC,CAAC,CAAC,CAAC,CAAC,CAAC,CAAC,CAAC,CAAC,CAAC,CAAC,CAAC,CAAC,CAAC,CAAC,CAAC,CAAC,CAAC,CAAC,CAAC,CAAC,CAAC,CAAC,CAAC,CAAC,CAAC,CAAC,CAAC,CAAC,CAAC,CAAC,CAAC,CAAC,CAAC,CAAC,CAAC,CAAC,CAAC,CAAC,CAAC,CAAC,CAAC,CAAC,CAAC,CAAC,CAAC,CAAC,CAAC,CAAC,CAAC,CAAC,CAAC,CAAC,CAAC,CAAC,CAAC,CAAC,CAAC,CAAC,CAAC,CAAC,CAAC,CAAC,CAAC,CAAC,CAAC,CAAC,CAAC,CAAC,CAAC,CAAC,CAAC,CAAC,CAAC,CAAC,CAAC,CAAC,CAAC,CAAC,CAAC,CAAC,CAAC,CAAC,CAAC,CAAC,CAAC,CAAC,CAAC;AACnJ;AACA,CAAC,CAAC,CAAC,CAAC,CAAC,CAAC,CAAC,CAAC,CAAC,CAAC,CAAC,CAAC,CAAC,CAAC,CAAC,CAAC,CAAC,CAAC,CAAC,CAAC,CAAC,CAAC,CAAC,CAAC,CAAC,CAAC,CAAC,CAAC,CAAC,CAAC,CAAC,CAAC,CAAC,CAAC,CAAC,CAAC,CAAC,CAAC,CAAC,CAAC,CAAC,CAAC,CAAC,CAAC,CAAC,CAAC,CAAC,CAAC,CAAC,CAAC,CAAC,CAAC,CAAC,CAAC,CAAC,CAAC,CAAC,CAAC,CAAC,CAAC,CAAC,CAAC,CAAC,CAAC,CAAC,CAAC,CAAC,CAAC,CAAC,CAAC,CAAC,CAAC,CAAC,CAAC,CAAC,CAAC,CAAC,CAAC,CAAC,CAAC,CAAC,CAAC,CAAC,CAAC,CAAC,CAAC,CAAC,CAAC;AACxF,CAAC,CAAC,CAAC,CAAC,CAAC,CAAC,CAAC,CAAC,CAAC,CAAC,CAAC,CAAC,CAAC,CAAC,CAAC,CAAC,CAAC,CAAC,CAAC,CAAC,CAAC,CAAC,CAAC,CAAC,CAAC,CAAC,CAAC,CAAC,CAAC,CAAC,CAAC,kBAA8B;AAC7D,CAAC,CAAC,CAAC,CAAC,CAAC,CAAC,CAAC,CAAC,CAAC,CAAC,CAAC,CAAC,CAAC,CAAC,CAAC,CAAC,CAAC,CAAC,CAAC,CAAC,CAAC,CAAC,CAAC,CAAC,CAAC,CAAC,CAAC,CAAC,CAAC,CAAC,CAAC,CAAC,CAAC,CAAC,CAAC,CAAC,CAAC,CAAC,CAAC,CAAC,CAAC,kBAAwC;AACjF,CAAC,CAAC,CAAC,CAAC,CAAC,CAAC,CAAC,CAAC,CAAC,CAAC,CAAC,CAAC,CAAC,CAAC,CAAC,CAAC,CAAC,CAAC,CAAC,CAAC,CAAC,CAAC,CAAC,CAAC,CAAC,CAAC,CAAC,CAAC,CAAC,CAAC,CAAC,CAAC,CAAC,kBAAgC;AACjE,CAAC,CAAC,CAAC,CAAC,CAAC,CAAC,CAAC,CAAC,CAAC,CAAC,CAAC,CAAC,CAAC,CAAC,CAAC,CAAC,CAAC,CAAC,CAAC,CAAC,CAAC,CAAC,CAAC,CAAC,CAAC,CAAC,CAAC,CAAC,CAAC,CAAC,CAAC,CAAC,CAAC,CAAC,CAAC,kBAAkC;AACrE,CAAC,CAAC,CAAC,CAAC,CAAC,CAAC,CAAC,CAAC,CAAC,CAAC,CAAC,CAAC,CAAC,CAAC,CAAC,CAAC,CAAC,CAAC,CAAC,CAAC,CAAC,CAAC,CAAC,CAAC,CAAC,CAAC,CAAC,CAAC,CAAC,CAAC,CAAC,CAAC,CAAC,CAAC,kBAAiC;AACnE,CAAC,CAAC,CAAC,CAAC,CAAC,CAAC,CAAC,CAAC,CAAC,CAAC,CAAC,CAAC,CAAC,CAAC,CAAC,CAAC,CAAC,CAAC,CAAC,CAAC,CAAC,CAAC,CAAC,CAAC,CAAC,CAAC,CAAC,CAAC,CAAC,CAAC,CAAC,CAAC,CAAC,CAAC,CAAC,CAAC,CAAC,kBAAoC;AACzE,CAAC,CAAC,CAAC,CAAC,CAAC,CAAC,CAAC,CAAC,CAAC,CAAC,CAAC,CAAC,CAAC,CAAC,CAAC,CAAC,CAAC,CAAC,CAAC,CAAC,CAAC,CAAC,CAAC,CAAC,CAAC,CAAC,CAAC,CAAC,CAAC,CAAC,CAAC,kBAA8B;AAC7D;AACA,CAAC,CAAC,CAAC,CAAC,CAAC,CAAC,CAAC,CAAC,CAAC,CAAC,CAAC,CAAC,CAAC,CAAC,CAAC,CAAC,CAAC,CAAC,CAAC,CAAC,CAAC,CAAC,CAAC,CAAC,CAAC,CAAC,CAAC,CAAC,CAAC,CAAC,CAAC,CAAC,CAAC,CAAC,CAAC,CAAC,CAAC,CAAC,CAAC,CAAC,CAAC,CAAC,CAAC,CAAC,CAAC,CAAC,CAAC,CAAC,CAAC,CAAC,CAAC,CAAC,CAAC,CAAC,CAAC,CAAC,CAAC,CAAC,CAAC,CAAC,CAAC,CAAC,CAAC,CAAC,CAAC,CAAC,CAAC,CAAC,CAAC,CAAC,CAAC,CAAC,CAAC,CAAC,CAAC,CAAC,CAAC,CAAC,CAAC,CAAC,CAAC,CAAC,CAAC,CAAC;AACpF,CAAC,CAAC,CAAC,CAAC,CAAC,CAAC,CAAC,CAAC,CAAC,CAAC,CAAC,CAAC,CAAC,CAAC,CAAC,CAAC,CAAC,CAAC,CAAC,CAAC,CAAC,CAAC,CAAC,CAAC,CAAC,CAAC,CAAC,CAAC,CAAC,CAAC,CAAC,CAAC,CAAC,CAAC,CAAC,CAAC,CAAC,CAAC,CAAC,CAAC,CAAC,CAAC,CAAC,CAAC,CAAC,CAAC,CAAC,CAAC,CAAC,CAAC,CAAC,CAAC,CAAC,CAAC,CAAC,CAAC,CAAC,CAAC,CAAC,CAAC,CAAC,CAAC,CAAC,CAAC,CAAC,CAAC,CAAC,CAAC,CAAC,CAAC,CAAC;AACvE,CAAC,CAAC,CAAC,CAAC,CAAC,CAAC,CAAC,CAAC,CAAC,CAAC,CAAC,CAAC,CAAC,CAAC,CAAC,CAAC,CAAC,CAAC,CAAC,CAAC,CAAC,CAAC,CAAC,CAAC,CAAC,CAAC,CAAC,CAAC,CAAC,CAAC,CAAC,CAAC,CAAC,CAAC,CAAC,CAAC,CAAC,CAAC,CAAC,CAAC,CAAC,CAAC,CAAC,CAAC,CAAC,CAAC,CAAC,CAAC,CAAC,CAAC,CAAC,CAAC,CAAC,CAAC,CAAC,CAAC,CAAC,CAAC,CAAC,CAAC,CAAC,CAAC,CAAC,CAAC,CAAC,CAAC,CAAC,CAAC,CAAC,CAAC,CAAC,CAAC,CAAC,CAAC,CAAC,CAAC,CAAC,CAAC,CAAC,CAAC,CAAC;AACjF,CAAC,CAAC,CAAC,CAAC,CAAC,CAAC,CAAC,CAAC,CAAC,CAAC,CAAC,CAAC,CAAC,CAAC,CAAC,CAAC,CAAC,CAAC,CAAC,CAAC,CAAC,CAAC,CAAC,CAAC,CAAC,CAAC,CAAC,CAAC,CAAC,CAAC,CAAC,CAAC,CAAC,CAAC,CAAC,CAAC,CAAC,CAAC,CAAC,CAAC,CAAC,CAAC,CAAC,CAAC,CAAC,CAAC,CAAC,CAAC,CAAC,CAAC,CAAC,CAAC,CAAC,CAAC,CAAC,CAAC,CAAC,CAAC,CAAC,CAAC,CAAC,CAAC,CAAC,CAAC,CAAC,CAAC,CAAC,CAAC,CAAC,CAAC,CAAC,CAAC,CAAC;AACzE,CAAC,CAAC,CAAC,CAAC,CAAC,CAAC,CAAC,CAAC,CAAC,CAAC,CAAC,CAAC,CAAC,CAAC,CAAC,CAAC,CAAC,CAAC,CAAC,CAAC,CAAC,CAAC,CAAC,CAAC,CAAC,CAAC,CAAC,CAAC,CAAC,CAAC,CAAC,CAAC,CAAC,CAAC,CAAC,CAAC,CAAC,CAAC,CAAC,CAAC,CAAC,CAAC,CAAC,CAAC,CAAC,CAAC,CAAC,CAAC,CAAC,CAAC,CAAC,CAAC,CAAC,CAAC,CAAC;AACvD,CAAC,CAAC,CAAC,CAAC,CAAC,CAAC,CAAC,CAAC,CAAC,CAAC,CAAC,CAAC,CAAC,CAAC,CAAC,CAAC,CAAC,CAAC,CAAC,CAAC,CAAC,CAAC,CAAC,CAAC,CAAC,CAAC,CAAC,CAAC,CAAC,CAAC,CAAC,CAAC;AAChC,CAAC,CAAC,CAAC,CAAC,CAAC,CAAC,CAAC,CAAC,CAAC,CAAC,CAAC,CAAC,CAAC,CAAC,CAAC,CAAC,CAAC,CAAC,CAAC,CAAC,CAAC,CAAC,CAAC,CAAC,CAAC,CAAC,CAAC,CAAC,CAAC,CAAC,CAAC,CAAC,CAAC,CAAC,CAAC,CAAC,CAAC,CAAC,CAAC,CAAC,CAAC,CAAC,CAAC,CAAC,CAAC,CAAC,CAAC,CAAC,CAAC,CAAC,CAAC,CAAC,CAAC,CAAC,CAAC,CAAC,CAAC,CAAC,CAAC,CAAC;AAC5D,CAAC,CAAC,CAAC,CAAC,CAAC,CAAC,CAAC,CAAC,CAAC,CAAC,CAAC,CAAC,CAAC,CAAC,CAAC,CAAC,CAAC,CAAC,CAAC,CAAC,CAAC,CAAC,CAAC,CAAC,CAAC,CAAC,CAAC,CAAC,CAAC,CAAC,CAAC,CAAC,CAAC,CAAC,CAAC,CAAC,CAAC,CAAC,CAAC,CAAC,CAAC,CAAC,CAAC,CAAC,CAAC,CAAC,CAAC,CAAC,CAAC,CAAC,CAAC,CAAC,CAAC,CAAC;AACtD,CAAC,CAAC,CAAC,CAAC,CAAC,CAAC,CAAC,CAAC,CAAC,CAAC,CAAC,CAAC,CAAC,CAAC,CAAC,CAAC,CAAC,CAAC,CAAC,CAAC;AACpB,CAAC,CAAC,CAAC,CAAC,CAAC,CAAC,CAAC,CAAC,CAAC,CAAC,CAAC,CAAC,CAAC,CAAC,CAAC,CAAC,CAAC,CAAC,CAAC,CAAC,CAAC,CAAC,CAAC,CAAC,CAAC,CAAC,CAAC,CAAC,CAAC,CAAC,CAAC,CAAC,CAAC,CAAC,CAAC,CAAC,CAAC,CAAC,CAAC,CAAC,CAAC,CAAC,CAAC,CAAC,CAAC,CAAC,CAAC,CAAC,CAAC,CAAC,CAAC,CAAC,CAAC,CAAC,CAAC,CAAC,CAAC,CAAC,CAAC,CAAC,CAAC,CAAC,CAAC,CAAC,CAAC,CAAC,CAAC,CAAC,CAAC,CAAC,CAAC,CAAC,CAAC,CAAC,CAAC,CAAC,CAAC,CAAC,CAAC,CAAC,CAAC,CAAC,CAAC,CAAC,CAAC,CAAC,CAAC,CAAC,CAAC,CAAC,CAAC,CAAC,CAAC,CAAC,CAAC,CAAC,CAAC,CAAC,CAAC,CAAC,CAAC,CAAC,CAAC,CAAC,CAAC,CAAC,CAAC,CAAC,CAAC,CAAC,CAAC,CAAC,CAAC,CAAC,CAAC,CAAC,CAAC,CAAC,CAAC,CAAC,CAAC,CAAC,CAAC,CAAC,CAAC,CAAC,CAAC,CAAC,CAAC,CAAC,CAAC,CAAC,CAAC,CAAC,CAAC,CAAC,CAAC,CAAC,CAAC,CAAC,CAAC,CAAC,CAAC,CAAC,CAAC,CAAC,CAAC,CAAC,CAAC,CAAC,CAAC,CAAC;AACxJ,CAAC,CAAC,CAAC,CAAC,CAAC,CAAC,CAAC,CAAC,CAAC,CAAC,CAAC,CAAC,CAAC,CAAC,CAAC,CAAC,CAAC,CAAC,CAAC,CAAC,CAAC,CAAC,CAAC,CAAC,CAAC,CAAC,CAAC,CAAC,CAAC,CAAC,CAAC,CAAC,CAAC,CAAC,CAAC,CAAC,CAAC,CAAC,CAAC,CAAC,CAAC,CAAC,CAAC,CAAC,CAAC,CAAC,CAAC,CAAC,CAAC,CAAC,CAAC;AACnD,CAAC,CAAC,CAAC,CAAC,CAAC,CAAC,CAAC,CAAC,CAAC,CAAC,CAAC,CAAC,CAAC,CAAC,CAAC,CAAC,CAAC,CAAC,CAAC,CAAC,CAAC,CAAC,CAAC,CAAC,CAAC,CAAC,CAAC,CAAC,CAAC,CAAC,CAAC,CAAC,CAAC,CAAC,CAAC,CAAC;AACpC,CAAC,CAAC,CAAC,CAAC,CAAC,CAAC,CAAC,CAAC,CAAC,CAAC,CAAC,CAAC,CAAC,CAAC,CAAC,CAAC,CAAC,CAAC,CAAC,CAAC,CAAC,CAAC,CAAC,CAAC,CAAC,CAAC,CAAC,CAAC,CAAC,CAAC,CAAC,CAAC,CAAC,CAAC,CAAC,CAAC,CAAC,CAAC,CAAC,CAAC,CAAC,CAAC,CAAC,CAAC,CAAC,CAAC,CAAC,CAAC,CAAC,CAAC,CAAC,CAAC,CAAC,CAAC,CAAC,CAAC,CAAC,CAAC,CAAC,CAAC,CAAC,CAAC,CAAC,CAAC,CAAC,CAAC,CAAC,CAAC,CAAC,CAAC,CAAC,CAAC,CAAC,CAAC,CAAC,CAAC,CAAC,CAAC,CAAC,CAAC,CAAC,CAAC,CAAC,CAAC,CAAC,CAAC;AACtF,CAAC,CAAC,CAAC,CAAC,CAAC,CAAC,CAAC,CAAC,CAAC,CAAC,CAAC,CAAC,CAAC,CAAC,CAAC,CAAC,CAAC,CAAC,CAAC;AACnB,CAAC,CAAC,CAAC,CAAC;AACJ,CAAC,CAAC,CAAC,CAAC,CAAC,CAAC,CAAC,CAAC,CAAC,CAAC,CAAC,CAAC,CAAC,CAAC,CAAC,CAAC,CAAC,CAAC,CAAC,CAAC,CAAC,CAAC,CAAC,CAAC,CAAC,CAAC,CAAC,CAAC,CAAC,CAAC,CAAC,CAAC,CAAC,CAAC,CAAC,CAAC,CAAC,CAAC,CAAC,CAAC,CAAC,CAAC,CAAC,CAAC,CAAC,CAAC,CAAC,CAAC,CAAC,CAAC,CAAC,CAAC,CAAC,CAAC,CAAC,CAAC,CAAC,CAAC,CAAC,CAAC,CAAC,CAAC,CAAC,CAAC,CAAC,CAAC,CAAC,CAAC,CAAC,CAAC,CAAC,CAAC,CAAC,CAAC,CAAC,CAAC,CAAC,CAAC,CAAC,CAAC,CAAC,CAAC,CAAC,CAAC,CAAC,CAAC,CAAC,CAAC,CAAC,CAAC,CAAC,CAAC,CAAC,CAAC,CAAC,CAAC,CAAC,CAAC,CAAC,CAAC,CAAC,CAAC,CAAC,CAAC,CAAC,CAAC,CAAC,CAAC,CAAC,CAAC,CAAC,CAAC,CAAC,CAAC,CAAC,CAAC,CAAC,CAAC,CAAC,CAAC,CAAC,CAAC,CAAC,CAAC,CAAC,CAAC,CAAC,CAAC,CAAC,CAAC,CAAC,CAAC,CAAC,CAAC,CAAC,CAAC,CAAC,CAAC,CAAC,CAAC,CAAC,CAAC,CAAC,CAAC,CAAC,CAAC,CAAC,CAAC,CAAC,CAAC,CAAC,CAAC,CAAC,CAAC,CAAC,CAAC,CAAC,CAAC,CAAC,CAAC,CAAC,CAAC,CAAC,CAAC,CAAC,CAAC,CAAC,CAAC,CAAC,CAAC,CAAC,CAAC,CAAC,CAAC,CAAC,CAAC,CAAC,CAAC,CAAC,CAAC,CAAC,CAAC,CAAC,CAAC,CAAC,CAAC,CAAC,CAAC,CAAC,CAAC,CAAC,CAAC,CAAC,CAAC,CAAC,CAAC,CAAC,CAAC,CAAC,CAAC,CAAC,CAAC,CAAC,CAAC,CAAC,CAAC,CAAC,CAAC,CAAC,CAAC,CAAC,CAAC,CAAC,CAAC,CAAC,CAAC,CAAC,CAAC,CAAC,CAAC,CAAC,CAAC,CAAC,CAAC,CAAC,CAAC,CAAC,CAAC,CAAC,CAAC,CAAC,CAAC,CAAC,CAAC,CAAC,CAAC,CAAC,CAAC,CAAC,CAAC,CAAC,CAAC,CAAC,CAAC,CAAC,CAAC,CAAC,CAAC,CAAC,CAAC,CAAC,CAAC,CAAC,CAAC,CAAC,CAAC,CAAC,CAAC,CAAC,CAAC,CAAC,CAAC,CAAC,CAAC,CAAC,CAAC,CAAC,CAAC,CAAC,CAAC,CAAC,CAAC,CAAC,CAAC,CAAC,CAAC,CAAC,CAAC,CAAC,CAAC,CAAC,CAAC,CAAC,CAAC,CAAC,CAAC,CAAC,CAAC,CAAC,CAAC,CAAC,CAAC,CAAC,CAAC,CAAC,CAAC,CAAC,CAAC,CAAC,CAAC,CAAC,CAAC,CAAC,CAAC,CAAC,CAAC,CAAC,CAAC,CAAC,CAAC,CAAC,CAAC,CAAC,CAAC,CAAC,CAAC,CAAC,CAAC,CAAC,CAAC,CAAC,CAAC,CAAC,CAAC,CAAC,CAAC,CAAC,CAAC,CAAC,CAAC,CAAC,CAAC,CAAC,CAAC,CAAC,CAAC,CAAC,CAAC,CAAC,CAAC,CAAC,CAAC,CAAC,CAAC,CAAC,CAAC,CAAC,CAAC,CAAC,CAAC,CAAC,CAAC,CAAC,CAAC,CAAC,CAAC,CAAC,CAAC,CAAC,CAAC,CAAC,CAAC,CAAC,CAAC,CAAC,CAAC,CAAC,CAAC,CAAC,CAAC,CAAC,CAAC,CAAC,CAAC,CAAC,CAAC,CAAC,CAAC,CAAC,CAAC,CAAC,CAAC,CAAC,CAAC,CAAC,CAAC,CAAC,CAAC,CAAC,CAAC,CAAC,CAAC,CAAC,CAAC,CAAC,CAAC,CAAC,CAAC,CAAC,CAAC,CAAC,CAAC,CAAC,CAAC,CAAC,CAAC,CAAC,CAAC,CAAC,CAAC,CAAC,CAAC,CAAC,CAAC;AAC9Z,CAAC,CAAC,CAAC,CAAC,CAAC,CAAC,CAAC,CAAC,CAAC,CAAC,CAAC,CAAC,CAAC,CAAC,CAAC,CAAC,CAAC,CAAC,CAAC,CAAC,CAAC,CAAC,CAAC,CAAC,CAAC,CAAC,CAAC,CAAC,CAAC,CAAC,CAAC,CAAC,CAAC,CAAC,CAAC,CAAC,CAAC,CAAC,CAAC,CAAC,CAAC,CAAC,CAAC,CAAC,CAAC,CAAC,CAAC,CAAC,CAAC,CAAC,CAAC,CAAC,CAAC,CAAC,CAAC,CAAC,CAAC,CAAC,CAAC,CAAC,CAAC,CAAC,CAAC,CAAC,CAAC,CAAC,CAAC,CAAC,CAAC,CAAC,CAAC,CAAC,CAAC,CAAC,CAAC,CAAC,CAAC;AAC7E,CAAC,CAAC,CAAC,CAAC,CAAC,CAAC,CAAC,CAAC,CAAC,CAAC,CAAC,CAAC,CAAC,CAAC,CAAC,CAAC,CAAC,CAAC,CAAC,CAAC,CAAC,CAAC,CAAC,CAAC,CAAC,CAAC,CAAC,CAAC,CAAC,CAAC,CAAC,CAAC,CAAC,CAAC,CAAC,CAAC,CAAC,CAAC,CAAC,CAAC,CAAC,CAAC,CAAC,CAAC,CAAC,CAAC,CAAC,CAAC,CAAC,CAAC,CAAC,CAAC,CAAC,CAAC,CAAC,CAAC,CAAC,CAAC,CAAC,CAAC,CAAC,CAAC,CAAC,CAAC,CAAC,CAAC,CAAC,CAAC,CAAC,CAAC,CAAC;AACvE,CAAC,CAAC,CAAC,CAAC,CAAC,CAAC,CAAC,CAAC,CAAC,CAAC,CAAC,CAAC,CAAC,CAAC,CAAC,CAAC,CAAC;AACjB,CAAC;AACD;AACA;AACA,CAAC,CAAC,CAAC,CAAC,CAAC,CAAC,CAAC,CAAC,CAAC,CAAC,CAAC,CAAC,CAAC,CAAC,CAAC,CAAC,CAAC,CAAC,CAAC,CAAC,CAAC,CAAC,CAAC,CAAC,CAAC,CAAC,CAAC,CAAC,CAAC,CAAC,CAAC,CAAC,CAAC,CAAC,CAAC,CAAC,CAAC,CAAC,CAAC,CAAC,CAAC,CAAC,CAAC,CAAC,CAAC,CAAC,CAAC,CAAC,CAAC,CAAC,CAAC,CAAC,CAAC,CAAC,CAAC,CAAC,CAAC,CAAC,CAAC;AAC3D,CAAC,CAAC,CAAC,CAAC,CAAC,CAAC,CAAC,CAAC,CAAC,CAAC,CAAC,CAAC,CAAC,CAAC,CAAC,CAAC,CAAC,CAAC,CAAC,CAAC,CAAC,CAAC,CAAC,CAAC,CAAC,CAAC,CAAC,CAAC,CAAC,CAAC,CAAC,CAAC,CAAC,CAAC;AAClC,CAAC,CAAC,CAAC,CAAC,CAAC,CAAC,CAAC,CAAC,CAAC,CAAC,CAAC,CAAC,CAAC,CAAC,CAAC,CAAC,CAAC,CAAC,CAAC,CAAC,CAAC,CAAC,CAAC,CAAC,CAAC,CAAC,CAAC,CAAC,CAAC,CAAC,CAAC,CAAC,CAAC,CAAC,CAAC;AACnC,CAAC,CAAC,CAAC,CAAC,CAAC,CAAC,CAAC,CAAC,CAAC,CAAC,CAAC,CAAC,CAAC,CAAC,CAAC,CAAC,CAAC,CAAC,CAAC,CAAC,CAAC,CAAC,CAAC,CAAC,CAAC,CAAC,CAAC,CAAC,CAAC,CAAC,CAAC,CAAC,CAAC,CAAC,CAAC,CAAC,CAAC,CAAC,CAAC,CAAC,CAAC,CAAC,CAAC;AAC3C,CAAC,CAAC,CAAC,CAAC,CAAC,CAAC,CAAC,CAAC,CAAC,CAAC,CAAC,CAAC,CAAC,CAAC,CAAC,CAAC,CAAC,CAAC,CAAC,CAAC,CAAC,CAAC,CAAC,CAAC,CAAC,CAAC,CAAC,CAAC,CAAC,CAAC,CAAC,CAAC,CAAC,CAAC,CAAC,CAAC,CAAC,CAAC,CAAC,CAAC,CAAC,CAAC,CAAC,CAAC,CAAC,CAAC,CAAC,CAAC,CAAC,CAAC,CAAC,CAAC,CAAC,CAAC,CAAC,CAAC,CAAC,CAAC,CAAC,CAAC,CAAC,CAAC,CAAC,CAAC,CAAC,CAAC,CAAC,CAAC,CAAC,CAAC,CAAC,CAAC,CAAC,CAAC,CAAC,CAAC,CAAC,CAAC,CAAC,CAAC,CAAC,CAAC,CAAC,CAAC,CAAC,CAAC,CAAC;AACvF,CAAC,CAAC,CAAC,CAAC,CAAC,CAAC,CAAC,CAAC,CAAC,CAAC,CAAC,CAAC,CAAC,CAAC,CAAC,CAAC,CAAC,CAAC,CAAC,CAAC,CAAC,CAAC,CAAC,CAAC,CAAC,CAAC,CAAC,CAAC,CAAC,CAAC,CAAC,CAAC,CAAC,CAAC,CAAC,CAAC,CAAC,CAAC,CAAC,CAAC,CAAC,CAAC,CAAC,CAAC,CAAC,CAAC,CAAC,CAAC,CAAC,CAAC,CAAC,CAAC,CAAC,CAAC,CAAC,CAAC;AACxD,CAAC;AACD,CAAC,CAAC,CAAC,CAAC,CAAC,CAAC,CAAC,CAAC,CAAC,CAAC,CAAC,CAAC,CAAC,CAAC,CAAC,CAAC,CAAC,CAAC,CAAC,CAAC,CAAC,CAAC,CAAC,CAAC,CAAC,CAAC,CAAC,CAAC,CAAC,CAAC,CAAC,CAAC,CAAC,CAAC,CAAC,CAAC,CAAC,CAAC,CAAC,CAAC,CAAC,CAAC,CAAC,CAAC,CAAC,CAAC,CAAC,CAAC,CAAC,CAAC,CAAC;AACnD,CAAC,CAAC,CAAC,CAAC,CAAC,CAAC,CAAC,CAAC,CAAC,CAAC,CAAC,CAAC,CAAC,CAAC,CAAC,CAAC,CAAC,CAAC,CAAC,CAAC,CAAC,CAAC,CAAC,CAAC,CAAC,CAAC,CAAC,CAAC,CAAC,CAAC,CAAC,CAAC,CAAC,CAAC,CAAC,CAAC,CAAC,CAAC,CAAC,CAAC,CAAC,CAAC,CAAC,CAAC,CAAC,CAAC,CAAC,CAAC,CAAC,CAAC,CAAC,CAAC,CAAC,CAAC,CAAC,CAAC,CAAC,CAAC,CAAC,CAAC,CAAC,CAAC,CAAC,CAAC,CAAC,CAAC,CAAC,CAAC,CAAC,CAAC,CAAC,CAAC,CAAC,CAAC,CAAC,CAAC,CAAC,CAAC,CAAC,CAAC,CAAC"
      }
    },
    {
      "name": "nuxt:tree-shake-composables:transform",
      "start": 1715842300020,
      "end": 1715842300020,
      "order": "post"
    },
    {
      "name": "vite:build-import-analysis",
      "start": 1715842300020,
      "end": 1715842300021,
      "order": "normal"
    },
    {
      "name": "vite:reporter",
      "start": 1715842300021,
      "end": 1715842300021,
      "order": "normal"
    }
  ]
}
